adcirc_rom/__init__.py
adcirc_rom/alaska.geojson
adcirc_rom/cli.py
adcirc_rom/constants.py
adcirc_rom/dataset.py
adcirc_rom/extract_best_tracks.py
adcirc_rom/features.py
adcirc_rom/gulf_coast.geojson
adcirc_rom/model.py
adcirc_rom/skeleton.py
adcirc_rom/stacked_model.py
adcirc_rom-0.0.0.dist-info/LICENSE.txt
adcirc_rom-0.0.0.dist-info/METADATA
adcirc_rom-0.0.0.dist-info/WHEEL
adcirc_rom-0.0.0.dist-info/entry_points.txt
adcirc_rom-0.0.0.dist-info/top_level.txt
adcirc_rom-0.0.0.dist-info/RECORD
