Metadata-Version: 2.1
Name: adcirc-rom
Version: 0.0.0
Summary: Add a short description here!
Home-page: https://github.com/pyscaffold/pyscaffold/
Author: Carlos del-Castillo-Negrete
Author-email: cdelcastillo21@gmail.com
License: MIT
Project-URL: Documentation, https://pyscaffold.org/
Platform: any
Classifier: Development Status :: 4 - Beta
Classifier: Programming Language :: Python
License-File: LICENSE.txt
Requires-Dist: netCDF4
Requires-Dist: scikit-learn
Requires-Dist: global-land-mask
Requires-Dist: xgboost
Requires-Dist: geopandas
Requires-Dist: scipy
Requires-Dist: h5py
Requires-Dist: fire
Requires-Dist: alive-progress
Requires-Dist: tensorflow
Requires-Dist: importlib-metadata ; python_version < "3.8"
Provides-Extra: testing
Requires-Dist: setuptools ; extra == 'testing'
Requires-Dist: pytest ; extra == 'testing'
Requires-Dist: pytest-cov ; extra == 'testing'
